compli_ai/__init__.py
compli_ai/inspector.py
compli_ai/main.py
compli_ai/orchestrator.py
compli_ai/reporter.py
compli_ai/schema.py
compli_ai-0.2.0.dist-info/METADATA
compli_ai-0.2.0.dist-info/WHEEL
compli_ai-0.2.0.dist-info/entry_points.txt
compli_ai-0.2.0.dist-info/RECORD
