Metadata-Version: 2.4
Name: compli-ai
Version: 0.2.0
Summary: Auto-generate EU AI Act technical documentation from your code.
Author: Compli-AI Team
Author-email: contact@example.com
Requires-Python: >=3.9,<4.0
Classifier: Programming Language :: Python :: 3
Classifier: Programming Language :: Python :: 3.9
Classifier: Programming Language :: Python :: 3.10
Classifier: Programming Language :: Python :: 3.11
Classifier: Programming Language :: Python :: 3.12
Classifier: Programming Language :: Python :: 3.13
Classifier: Programming Language :: Python :: 3.14
Requires-Dist: pydantic (>=2.12.5,<3.0.0)
Requires-Dist: pyyaml (>=6.0.3,<7.0.0)
Requires-Dist: rich (>=13.0.0,<14.0.0)
Requires-Dist: tomli (>=2.3.0,<3.0.0)
Requires-Dist: typer (>=0.9.0,<0.10.0)
Project-URL: Repository, https://github.com/yourusername/compli-ai
